falcon_json_rpc/__init__.py
falcon_json_rpc/config.py
falcon_json_rpc/decorators.py
falcon_json_rpc/errors.py
falcon_json_rpc/json_rpc.py
falcon_json_rpc/json_rpc_router.py
falcon_json_rpc/middleware.py
falcon_json_rpc/serializers.py
falcon_json_rpc/server.py
falcon_json_rpc/test.py
falcon_json_rpc/typing.py
falcon_json_rpc/util.py
falcon_json_rpc/validators.py
falcon_json_rpc-1.0.0.dist-info/LICENSE
falcon_json_rpc-1.0.0.dist-info/METADATA
falcon_json_rpc-1.0.0.dist-info/WHEEL
falcon_json_rpc-1.0.0.dist-info/top_level.txt
falcon_json_rpc-1.0.0.dist-info/RECORD
